rpmautospec_core/__init__.py
rpmautospec_core/main.py
rpmautospec_core-0.1.4.dist-info/LICENSE
rpmautospec_core-0.1.4.dist-info/METADATA
rpmautospec_core-0.1.4.dist-info/WHEEL
rpmautospec_core-0.1.4.dist-info/RECORD
