Metadata-Version: 2.1
Name: rpmautospec-core
Version: 0.1.4
Summary: Core functionality for rpmautospec
Home-page: https://github.com/fedora-infra/rpmautospec-core
License: MIT
Author: Nils Philippsen
Author-email: nils@redhat.com
Requires-Python: >=3.6,<4.0
Classifier: License :: OSI Approved :: MIT License
Classifier: Programming Language :: Python :: 3
Classifier: Programming Language :: Python :: 3.6
Classifier: Programming Language :: Python :: 3.7
Classifier: Programming Language :: Python :: 3.8
Classifier: Programming Language :: Python :: 3.9
Classifier: Programming Language :: Python :: 3.10
Classifier: Programming Language :: Python :: 3.11
Project-URL: Repository, https://github.com/fedora-infra/rpmautospec-core
